alegant/__init__.py
alegant/data_module.py
alegant/runner.py
alegant/trainer.py
alegant/utils.py
alegant-1.0.6.dist-info/LICENSE
alegant-1.0.6.dist-info/METADATA
alegant-1.0.6.dist-info/WHEEL
alegant-1.0.6.dist-info/top_level.txt
alegant-1.0.6.dist-info/RECORD
