Metadata-Version: 2.1
Name: alegant
Version: 1.0.6
Summary: Alegant: a elegant training framework
Home-page: https://github.com/Hugo-Zhu/alegant
Author: Haohao Zhu
Author-email: zhuhh17@qq.com
License: MIT
Classifier: Programming Language :: Python :: 3
Classifier: License :: OSI Approved :: MIT License
Classifier: Operating System :: OS Independent
Requires-Python: >=3.7
License-File: LICENSE
Requires-Dist: attrdict
Requires-Dist: loguru
Requires-Dist: numpy
Requires-Dist: pyyaml
Requires-Dist: six
Requires-Dist: tensorboard
Requires-Dist: torch
Requires-Dist: tqdm
